{"name":"CSS 实现","slug":"CSS-实现","count":1,"postlist":[{"title":"mac三个小圆点之CSS实现","uid":"779b5ad4b4932e48cef7c8491a075b37","slug":"mac三个小圆点之CSS实现","date":"2022-06-20T06:26:04.000Z","updated":"2022-06-20T07:11:00.114Z","comments":true,"path":"api/articles/mac三个小圆点之CSS实现.json","keywords":null,"cover":null,"text":" 第一个小圆点可以使用 border-radius 实现一个小圆点: &lt;div class&#x3D;&quot;mac-menu-circle&quot;&gt;&lt;&#x2F;div&gt; div.mac-menu-circle &#123; width: 15p...","link":"","photos":[],"count_time":{"symbolsCount":660,"symbolsTime":"1 mins."},"categories":[],"tags":[{"name":"mac","slug":"mac","count":1,"path":"api/tags/mac.json"},{"name":"CSS 实现","slug":"CSS-实现","count":1,"path":"api/tags/CSS-实现.json"}],"author":{"name":"paranoia","slug":"blog-author","avatar":"https://img-blog.csdnimg.cn/20210313122054101.png","link":"https://321paranoiawhy.github.io","description":"生命不息, 笔耕不辍","socials":{"github":"","twitter":"","stackoverflow":"","wechat":"","qq":"","weibo":"","zhihu":"","csdn":"","juejin":"","customs":{}}},"feature":true}]}